{
  "$schema": "https://developer.microsoft.com/json-schemas/fabric/item/report/definition/visualContainer/2.5.0/schema.json",
  "name": "c1e0a3a5c41cd1fcfca8",
  "position": {
    "x": 0,
    "y": 414.32394366197184,
    "z": 2000,
    "height": 144.11267605633802,
    "width": 204.91021126760563,
    "tabOrder": 20000
  },
  "visual": {
    "visualType": "basicShape",
    "objects": {
      "general": [
        {
          "properties": {
            "shapeType": {
              "expr": {
                "Literal": {
                  "Value": "'rectangle'"
                }
              }
            }
          }
        }
      ],
      "fill": [
        {
          "properties": {
            "show": {
              "expr": {
                "Literal": {
                  "Value": "false"
                }
              }
            }
          }
        }
      ],
      "line": [
        {
          "properties": {
            "weight": {
              "expr": {
                "Literal": {
                  "Value": "20D"
                }
              }
            }
          }
        }
      ]
    }
  },
  "isHidden": true
}