{
  "$schema": "https://developer.microsoft.com/json-schemas/fabric/item/report/definition/visualContainer/2.5.0/schema.json",
  "name": "84bfef789ac0f9277c0b",
  "position": {
    "x": 163.71200000000002,
    "y": 432.66742857142862,
    "z": 7000,
    "height": 29.234285714285715,
    "width": 1011.5062857142858,
    "tabOrder": 12000
  },
  "visual": {
    "visualType": "basicShape",
    "objects": {
      "general": [
        {
          "properties": {
            "shapeType": {
              "expr": {
                "Literal": {
                  "Value": "'line'"
                }
              }
            }
          }
        }
      ],
      "fill": [
        {
          "properties": {
            "show": {
              "expr": {
                "Literal": {
                  "Value": "false"
                }
              }
            }
          }
        }
      ],
      "line": [
        {
          "properties": {
            "weight": {
              "expr": {
                "Literal": {
                  "Value": "11D"
                }
              }
            }
          }
        }
      ],
      "rotation": [
        {
          "properties": {
            "angle": {
              "expr": {
                "Literal": {
                  "Value": "90D"
                }
              }
            }
          }
        }
      ]
    }
  },
  "isHidden": true
}